lazop_sdk/__init__.py
lazop_sdk/base.py
lazop_sdk-1.0.2.dist-info/METADATA
lazop_sdk-1.0.2.dist-info/WHEEL
lazop_sdk-1.0.2.dist-info/top_level.txt
lazop_sdk-1.0.2.dist-info/RECORD
