Metadata-Version: 2.1
Name: lazop-sdk
Version: 1.0.2
Summary: Lazada Official SDK
Home-page: https://github.com/PsKs/lazop-sdk
Author: Pongsakorn
Author-email: pongsakorn.psks@gmail.com
License: README.md
Platform: UNKNOWN
Classifier: License :: OSI Approved :: MIT License
Classifier: Programming Language :: Python :: 3
Classifier: Programming Language :: Python :: 3.7
Requires-Dist: requests
